geo_intel_offline/__init__.py
geo_intel_offline/api.py
geo_intel_offline/compression.py
geo_intel_offline/confidence.py
geo_intel_offline/data_builder.py
geo_intel_offline/data_builder_minimal.py
geo_intel_offline/data_builder_modular.py
geo_intel_offline/data_loader.py
geo_intel_offline/geohash.py
geo_intel_offline/migrate_to_modular.py
geo_intel_offline/modular_data_loader.py
geo_intel_offline/pip.py
geo_intel_offline/polygon_utils.py
geo_intel_offline/resolver.py
geo_intel_offline/reverse_resolver.py
geo_intel_offline/data/geohash_index.json.gz
geo_intel_offline/data/metadata.json.gz
geo_intel_offline/data/polygons.json.gz
geo_intel_offline-1.4.1.dist-info/LICENSE
geo_intel_offline-1.4.1.dist-info/METADATA
geo_intel_offline-1.4.1.dist-info/WHEEL
geo_intel_offline-1.4.1.dist-info/entry_points.txt
geo_intel_offline-1.4.1.dist-info/top_level.txt
geo_intel_offline-1.4.1.dist-info/RECORD
