Metadata-Version: 2.1
Name: geo-intel-offline
Version: 1.4.1
Summary: Production-ready, offline geo-intelligence library for resolving latitude/longitude to country, ISO codes, continent, and timezone information
Home-page: https://github.com/RRJena/geo-intel-offline
Author: Rakesh Ranjan Jena
Author-email: Rakesh Ranjan Jena <rakesh@rrjprince.com>
License: MIT
Project-URL: Homepage, https://github.com/RRJena/geo-intel-offline
Project-URL: Documentation, https://github.com/RRJena/geo-intel-offline#readme
Project-URL: Repository, https://github.com/RRJena/geo-intel-offline
Project-URL: Issues, https://github.com/RRJena/geo-intel-offline/issues
Project-URL: Bug Tracker, https://github.com/RRJena/geo-intel-offline/issues
Keywords: geolocation,geography,country,iso,timezone,offline,geohash
Classifier: Development Status :: 5 - Production/Stable
Classifier: Intended Audience :: Developers
Classifier: License :: OSI Approved :: MIT License
Classifier: Programming Language :: Python :: 3
Classifier: Programming Language :: Python :: 3.8
Classifier: Programming Language :: Python :: 3.9
Classifier: Programming Language :: Python :: 3.10
Classifier: Programming Language :: Python :: 3.11
Classifier: Programming Language :: Python :: 3.12
Classifier: Topic :: Scientific/Engineering :: GIS
Classifier: Topic :: Software Development :: Libraries :: Python Modules
Requires-Python: >=3.8
License-File: LICENSE
Provides-Extra: dev
Requires-Dist: black >=23.0 ; extra == 'dev'
Requires-Dist: mypy >=1.0 ; extra == 'dev'
Requires-Dist: pytest-cov >=4.0 ; extra == 'dev'
Requires-Dist: pytest >=7.0 ; extra == 'dev'
